{"_path":"/blogs/2022-05-31-hasil-survei-kos-bem-uns-2022","_draft":false,"_partial":false,"_locale":"id","_empty":false,"title":"HASIL SURVEI KOS BEM UNS 2022","description":" HASIL SURVEI KOS BEM UNS 2022","excerpt":{"type":"root","children":[{"type":"element","tag":"p","props":{},"children":[{"type":"element","tag":"span","props":{},"children":[{"type":"text","value":" HASIL SURVEI KOS BEM UNS 2022"}]}]},{"type":"element","tag":"p","props":{},"children":[{"type":"text","value":"Hiii Datalkers 👋🏻"}]},{"type":"element","tag":"p","props":{},"children":[{"type":"text","value":"Kalian pernah bingung ga sih mau tidur dimana? Mau tidur di rumah temen tapi merasa ga enak, mau tidur di sekre tapi badan langsung pegal-pegal karena kedinginan dan tidak ada kasur, mau tidur di mesjid tapi agamanya beda. Namun, tenang saja.. tidak perlu panik, BEM UNS 2022 melalui Kementerian Riset dan Data telah melakukan survei kos untuk membantu kalian yang merantau, jauh dari rumah, maupun diusir keluarga."}]},{"type":"element","tag":"p","props":{},"children":[{"type":"text","value":"Sebelumnya, terimakasih kepada seluruh responden yang telah berkontribusi survei kos kali ini ✨"}]},{"type":"element","tag":"p","props":{},"children":[{"type":"text","value":"Berikut adalah hasil survei kos BEM UNS 2022:"}]},{"type":"element","tag":"iframe","props":{"src":"https://mozilla.github.io/pdf.js/web/viewer.html?file=https://datalks.bemuns.org/blog/HasilSurveiKosUNS2022.pdf"},"children":[]}]},"date":"2022-05-31T00:00:00.000Z","image":"/blog/SURVEIKOSBEMUNSTAHUN2022.webp","body":{"type":"root","children":[{"type":"element","tag":"p","props":{},"children":[{"type":"element","tag":"span","props":{},"children":[{"type":"text","value":" HASIL SURVEI KOS BEM UNS 2022"}]}]},{"type":"element","tag":"p","props":{},"children":[{"type":"text","value":"Hiii Datalkers 👋🏻"}]},{"type":"element","tag":"p","props":{},"children":[{"type":"text","value":"Kalian pernah bingung ga sih mau tidur dimana? Mau tidur di rumah temen tapi merasa ga enak, mau tidur di sekre tapi badan langsung pegal-pegal karena kedinginan dan tidak ada kasur, mau tidur di mesjid tapi agamanya beda. Namun, tenang saja.. tidak perlu panik, BEM UNS 2022 melalui Kementerian Riset dan Data telah melakukan survei kos untuk membantu kalian yang merantau, jauh dari rumah, maupun diusir keluarga."}]},{"type":"element","tag":"p","props":{},"children":[{"type":"text","value":"Sebelumnya, terimakasih kepada seluruh responden yang telah berkontribusi survei kos kali ini ✨"}]},{"type":"element","tag":"p","props":{},"children":[{"type":"text","value":"Berikut adalah hasil survei kos BEM UNS 2022:"}]},{"type":"element","tag":"iframe","props":{"src":"https://mozilla.github.io/pdf.js/web/viewer.html?file=https://datalks.bemuns.org/blog/HasilSurveiKosUNS2022.pdf"},"children":[]}],"toc":{"title":"","searchDepth":2,"depth":2,"links":[]}},"_type":"markdown","_id":"content:blogs:2022-05-31-HASIL-SURVEI-KOS-BEM-UNS-2022.md","_source":"content","_file":"blogs/2022-05-31-HASIL-SURVEI-KOS-BEM-UNS-2022.md","_extension":"md"}